LICENSE.txt
MANIFEST.in
README.txt
setup.py
BuffetMyghty.egg-info/PKG-INFO
BuffetMyghty.egg-info/SOURCES.txt
BuffetMyghty.egg-info/dependency_links.txt
BuffetMyghty.egg-info/entry_points.txt
BuffetMyghty.egg-info/not-zip-safe
BuffetMyghty.egg-info/top_level.txt
buffetmyghty/__init__.py
buffetmyghty/myghtysupport.py
test/test.py
test/templates/extra_vars.myt
test/templates/myghty_test.myt
