Metadata-Version: 1.0
Name: BuffetMyghty
Version: 0.3
Summary: Myghty templating language plugin
Home-page: http://projects.dowski.com/projects/buffetmyghty
Author: Christian Wyglendowski
Author-email: christian@dowski.com
License: MIT
Platform: UNKNOWN
